NiChart_Viewer/NiChart_Viewer_CmdApp.py
NiChart_Viewer/__init__.py
NiChart_Viewer/__main__.py
NiChart_Viewer/aboutdialog.py
NiChart_Viewer/aboutdialog.ui
NiChart_Viewer/mainwindow.py
NiChart_Viewer/mainwindow.ui
NiChart_Viewer/core/__init__.py
NiChart_Viewer/core/baseplugin.py
NiChart_Viewer/core/dataio.py
NiChart_Viewer/core/datautils.py
NiChart_Viewer/core/iStagingLogger.py
NiChart_Viewer/core/plotcanvas.py
NiChart_Viewer/core/gui/CheckableQComboBox.py
NiChart_Viewer/core/gui/NestedCheckableQComboBox.py
NiChart_Viewer/core/gui/NestedQMenu.py
NiChart_Viewer/core/gui/QColorTable.py
NiChart_Viewer/core/gui/SearchableQComboBox.py
NiChart_Viewer/core/gui/__init__.py
NiChart_Viewer/core/model/__init__.py
NiChart_Viewer/core/model/cmdmodel.py
NiChart_Viewer/core/model/datamodel.py
NiChart_Viewer/plugins/__init__.py
NiChart_Viewer/plugins/centileview/__init__.py
NiChart_Viewer/plugins/centileview/centileview.py
NiChart_Viewer/plugins/centileview/centileview.ui
NiChart_Viewer/plugins/centileview/centileview.yapsy-plugin
NiChart_Viewer/plugins/dsetview/__init__.py
NiChart_Viewer/plugins/dsetview/dsetview.py
NiChart_Viewer/plugins/dsetview/dsetview.ui
NiChart_Viewer/plugins/dsetview/dsetview.yapsy-plugin
NiChart_Viewer/plugins/icvcorrview/__init__.py
NiChart_Viewer/plugins/icvcorrview/icvcorrview.py
NiChart_Viewer/plugins/icvcorrview/icvcorrview.ui
NiChart_Viewer/plugins/icvcorrview/icvcorrview.yapsy-plugin
NiChart_Viewer/plugins/mergeview/__init__.py
NiChart_Viewer/plugins/mergeview/mergeview.py
NiChart_Viewer/plugins/mergeview/mergeview.ui
NiChart_Viewer/plugins/mergeview/mergeview.yapsy-plugin
NiChart_Viewer/plugins/plotview/__init__.py
NiChart_Viewer/plugins/plotview/plotview.py
NiChart_Viewer/plugins/plotview/plotview.ui
NiChart_Viewer/plugins/plotview/plotview.yapsy-plugin
NiChart_Viewer/resources/__init__.py
NiChart_Viewer/resources/nichart_logo_s1.png
NiChart_Viewer/resources/nichart_viewer_ixi_example.png
NiChart_Viewer/resources/nichart_viewer_logo_s1.png
NiChart_Viewer-1.0.4.dist-info/LICENSE
NiChart_Viewer-1.0.4.dist-info/METADATA
NiChart_Viewer-1.0.4.dist-info/WHEEL
NiChart_Viewer-1.0.4.dist-info/entry_points.txt
NiChart_Viewer-1.0.4.dist-info/top_level.txt
NiChart_Viewer-1.0.4.dist-info/RECORD
